airflow_provider_hex/__init__.py
airflow_provider_hex/types.py
airflow_provider_hex/hooks/__init__.py
airflow_provider_hex/hooks/hex.py
airflow_provider_hex/operators/__init__.py
airflow_provider_hex/operators/hex.py
airflow_provider_hex-0.1.9.dist-info/METADATA
airflow_provider_hex-0.1.9.dist-info/WHEEL
airflow_provider_hex-0.1.9.dist-info/entry_points.txt
airflow_provider_hex-0.1.9.dist-info/top_level.txt
airflow_provider_hex-0.1.9.dist-info/RECORD
