Metadata-Version: 2.1
Name: airflow-provider-hex
Version: 0.1.9
Summary: Apache Airflow Hex provider containing Hooks and Operators
Home-page: https://github.com/hex-inc/airflow-provider-hex
Author: Pedram Navid
Author-email: pedram@pedramnavid.com
License: Apache License 2.0
Project-URL: Source Code, https://github.com/hex-inc/airflow-provider-hex
Project-URL: Homepage, https://github.com/hex-inc/airflow-provider-hex
Project-URL: Changelog, https://github.com/hex-inc/airflow-provider-hex/blob/main/CHANGELOG.md
Classifier: Environment :: Web Environment
Classifier: Intended Audience :: Developers
Classifier: Operating System :: OS Independent
Classifier: Programming Language :: Python
Requires-Python: >=3.7
Requires-Dist: apache-airflow (>=2.2.0)
Requires-Dist: requests (>=2)
Requires-Dist: importlib-metadata (>=4.8.1)
Requires-Dist: typing-extensions (>=3.10.0.2)
Provides-Extra: dev
Requires-Dist: mypy (>=0.8) ; extra == 'dev'
Requires-Dist: pytest ; extra == 'dev'
Requires-Dist: pre-commit ; extra == 'dev'
Requires-Dist: flake8 ; extra == 'dev'
Requires-Dist: isort ; extra == 'dev'
Requires-Dist: types-requests ; extra == 'dev'
Requires-Dist: black ; extra == 'dev'
Requires-Dist: pytest-mock ; extra == 'dev'
Requires-Dist: requests-mock ; extra == 'dev'
